libpxblat.cpython-310-darwin.so
pxblat/__init__.py
pxblat/parser.py
pxblat/py.typed
pxblat/_extc.cpython-310-darwin.so
pxblat/server/server.py
pxblat/server/client.py
pxblat/server/__init__.py
pxblat/server/basic.py
pxblat/server/utils.py
pxblat/server/status.py
pxblat/cli/twobit2fa.py
pxblat/cli/server.py
pxblat/cli/log.py
pxblat/cli/client.py
pxblat/cli/__init__.py
pxblat/cli/cli.py
pxblat/cli/fa2twobit.py
pxblat/.dylibs/libssl.3.dylib
pxblat/.dylibs/libcrypto.3.dylib
pxblat/extc/gfClient.c
pxblat/extc/__init__.pyi
pxblat/extc/twoBitToFa.c
pxblat/extc/__init__.py
pxblat/extc/faToTwoBit.c
pxblat/extc/blat.c
pxblat/extc/gfServer.c
pxblat/extc/include/.clang-format
pxblat/extc/include/net/gfNet.h
pxblat/extc/include/net/log.h
pxblat/extc/include/core/chain.h
pxblat/extc/include/core/maf.h
pxblat/extc/include/core/udc.h
pxblat/extc/include/core/sqlNum.h
pxblat/extc/include/core/net.h
pxblat/extc/include/core/asParse.h
pxblat/extc/include/core/twoBit.h
pxblat/extc/include/core/gfInternal.h
pxblat/extc/include/core/sqlList.h
pxblat/extc/include/core/verbose.h
pxblat/extc/include/core/dlist.h
pxblat/extc/include/core/trans3.h
pxblat/extc/include/core/tokenizer.h
pxblat/extc/include/core/errCatch.h
pxblat/extc/include/core/options.h
pxblat/extc/include/core/dnautil.h
pxblat/extc/include/core/basicBed.h
pxblat/extc/include/core/rangeTree.h
pxblat/extc/include/core/binRange.h
pxblat/extc/include/core/fuzzyFind.h
pxblat/extc/include/core/supStitch.h
pxblat/extc/include/core/gfClientLib.h
pxblat/extc/include/core/linefile.h
pxblat/extc/include/core/repMask.h
pxblat/extc/include/core/ooc.h
pxblat/extc/include/core/sig.h
pxblat/extc/include/core/common.h
pxblat/extc/include/core/netlib.h
pxblat/extc/include/core/dystring.h
pxblat/extc/include/core/nib.h
pxblat/extc/include/core/psl.h
pxblat/extc/include/core/portable.h
pxblat/extc/include/core/genoFind.h
pxblat/extc/include/core/pipeline.h
pxblat-1.2.1.dist-info/RECORD
pxblat-1.2.1.dist-info/LICENSE
pxblat-1.2.1.dist-info/WHEEL
pxblat-1.2.1.dist-info/entry_points.txt
pxblat-1.2.1.dist-info/METADATA
