Metadata-Version: 2.1
Name: pxblat
Version: 1.2.1
Summary: A native python binding for blat suite
Home-page: https://github.com/ylab-hi/pxblat
License: LICENSE
Keywords: bioinformatics,sequence aligner,blat
Author: Yangyang Li
Author-email: yangyang.li@northwestern.edu
Requires-Python: >=3.9,<3.12
Classifier: Development Status :: 6 - Mature
Classifier: License :: Other/Proprietary License
Classifier: Operating System :: MacOS :: MacOS X
Classifier: Operating System :: POSIX :: Linux
Classifier: Programming Language :: C
Classifier: Programming Language :: C++
Classifier: Programming Language :: Python :: 3
Classifier: Programming Language :: Python :: 3.9
Classifier: Programming Language :: Python :: 3.10
Classifier: Programming Language :: Python :: 3.11
Classifier: Programming Language :: Python :: 3 :: Only
Requires-Dist: biopython (>=1.81,<2.0)
Requires-Dist: deprecated (>=1.2.13,<2.0.0)
Requires-Dist: loguru (>=0.7.0,<0.8.0)
Requires-Dist: mashumaro (>=3.7,<4.0)
Requires-Dist: pybind11 (>=2.10.4,<3.0.0)
Requires-Dist: pysimdjson (>=5.0.2,<7.0.0)
Requires-Dist: rich (>=13.3.5,<14.0.0)
Requires-Dist: setuptools (>=68.2.2,<70.0.0)
Requires-Dist: typer (>=0.9,<0.13)
Requires-Dist: urllib3 (==2.2.1)
Project-URL: Documentation, https://pxblat.readthedocs.io/en/latest/
Project-URL: Repository, https://github.com/ylab-hi/pxblat
